LICENCE
README.md
setup.py
MixMasterEngine/__init__.py
MixMasterEngine/app/functions.py
MixMasterEngine/app/LogDB/__init__.py
MixMasterEngine/app/LogDB/models.py
MixMasterEngine/app/Member/__init__.py
MixMasterEngine/app/Member/models.py
MixMasterEngine/app/Profile/__init__.py
MixMasterEngine/app/Profile/models.py
MixMasterEngine/app/S_Data/__init__.py
MixMasterEngine/app/S_Data/models.py
MixMasterEngine/app/Web_Account/__init__.py
MixMasterEngine/app/Web_Account/models.py
MixMasterEngine/app/gamedata/__init__.py
MixMasterEngine/app/gamedata/models.py
mixmaster_engine.egg-info/PKG-INFO
mixmaster_engine.egg-info/SOURCES.txt
mixmaster_engine.egg-info/dependency_links.txt
mixmaster_engine.egg-info/requires.txt
mixmaster_engine.egg-info/top_level.txt